{
  "media": {
    "media_uuid": "374ff712-d61b-4ca5-81f6-10f3526744e9",
    "checksum": "ea52a2b63f0e6fe94bd6a6685feb06f8dafc877e989c3dd601f41a312745bc8d",
    "faces": [
      {
        "face_uuid": "36ac8fde-1536-11e9-99c4-0cc47a6c4dbd",
        "media_uuid": "374ff712-d61b-4ca5-81f6-10f3526744e9",
        "x": 628.75,
        "y": 171.25,
        "width": 172.2,
        "height": 236.77,
        "angle": -1.7798,
        "detection_score": 1.0,
        "points": [
          {
            "x": 620.91,
            "y": 147.54,
            "type": 512,
            "name": "basic eye left"
          },
          {
            "x": 697.99,
            "y": 149.94,
            "type": 768,
            "name": "basic eye right"
          },
          {
            "x": 602.81,
            "y": 147.54,
            "type": 1024,
            "name": "basic eye left outer"
          },
          {
            "x": 713.7,
            "y": 150.91,
            "type": 1280,
            "name": "basic eye right outer"
          },
          {
            "x": 638.37,
            "y": 148.06,
            "type": 1536,
            "name": "basic eye left inner"
          },
          {
            "x": 682.45,
            "y": 149.45,
            "type": 1792,
            "name": "basic eye right inner"
          },
          {
            "x": 620.09,
            "y": 236.21,
            "type": 2048,
            "name": "basic mouth left"
          },
          {
            "x": 687.43,
            "y": 239.97,
            "type": 2304,
            "name": "basic mouth right"
          },
          {
            "x": 670.28,
            "y": 198.45,
            "type": 2560,
            "name": "basic nose tip"
          },
          {
            "x": 654.67,
            "y": 238.47,
            "type": 2816,
            "name": "basic mouth center"
          },
          {
            "x": 654.67,
            "y": 238.47,
            "type": 3072,
            "name": "basic eyebrow left"
          },
          {
            "x": 654.67,
            "y": 238.47,
            "type": 3328,
            "name": "basic eyebrow left inner corner"
          },
          {
            "x": 654.67,
            "y": 238.47,
            "type": 3584,
            "name": "basic eyebrow left outer corner"
          },
          {
            "x": 654.67,
            "y": 238.47,
            "type": 3840,
            "name": "basic eyebrow right"
          },
          {
            "x": 654.67,
            "y": 238.47,
            "type": 4096,
            "name": "basic eyebrow right inner corner"
          },
          {
            "x": 654.67,
            "y": 238.47,
            "type": 4352,
            "name": "basic eyebrow right outer corner"
          },
          {
            "x": 654.67,
            "y": 238.47,
            "type": 4608,
            "name": "basic chin bottom"
          },
          {
            "x": 654.67,
            "y": 238.47,
            "type": 4864,
            "name": "basic chin left"
          },
          {
            "x": 654.67,
            "y": 238.47,
            "type": 5120,
            "name": "basic chin right"
          },
          {
            "x": 644.44,
            "y": 202.79,
            "type": 5376,
            "name": "basic nose left"
          },
          {
            "x": 685.3,
            "y": 204.47,
            "type": 5632,
            "name": "basic nose right"
          }
        ],
        "user_points": null,
        "tags": [
          {
            "name": "5oclock shadow",
            "value": "no",
            "confidence": 1.0
          },
          {
            "name": "age",
            "value": "31",
            "confidence": 0.6
          },
          {
            "name": "arched eyebrows",
            "value": "no",
            "confidence": 0.12
          },
          {
            "name": "attractive",
            "value": "yes",
            "confidence": 0.77
          },
          {
            "name": "bags under eyes",
            "value": "no",
            "confidence": 1.0
          },
          {
            "name": "bald",
            "value": "no",
            "confidence": 0.89
          },
          {
            "name": "bangs",
            "value": "no",
            "confidence": 0.54
          },
          {
            "name": "beard",
            "value": "no",
            "confidence": 1.0
          },
          {
            "name": "big lips",
            "value": "no",
            "confidence": 0.18
          },
          {
            "name": "big nose",
            "value": "no",
            "confidence": 1.0
          },
          {
            "name": "black hair",
            "value": "no",
            "confidence": 0.68
          },
          {
            "name": "blond hair",
            "value": "yes",
            "confidence": 0.79
          },
          {
            "name": "blurry",
            "value": "no",
            "confidence": 0.78
          },
          {
            "name": "brown hair",
            "value": "no",
            "confidence": 0.91
          },
          {
            "name": "bushy eyebrows",
            "value": "no",
            "confidence": 0.94
          },
          {
            "name": "chubby",
            "value": "no",
            "confidence": 1.0
          },
          {
            "name": "double chin",
            "value": "no",
            "confidence": 1.0
          },
          {
            "name": "expression",
            "value": "smile",
            "confidence": 0.92
          },
          {
            "name": "gender",
            "value": "female",
            "confidence": 1.0
          },
          {
            "name": "glasses",
            "value": "no",
            "confidence": 1.0
          },
          {
            "name": "goatee",
            "value": "no",
            "confidence": 1.0
          },
          {
            "name": "gray hair",
            "value": "no",
            "confidence": 0.7
          },
          {
            "name": "heavy makeup",
            "value": "yes",
            "confidence": 0.92
          },
          {
            "name": "high cheekbones",
            "value": "yes",
            "confidence": 0.68
          },
          {
            "name": "mouth open",
            "value": "yes",
            "confidence": 1.0
          },
          {
            "name": "mustache",
            "value": "no",
            "confidence": 1.0
          },
          {
            "name": "narrow eyes",
            "value": "no",
            "confidence": 0.71
          },
          {
            "name": "oval face",
            "value": "yes",
            "confidence": 0.62
          },
          {
            "name": "pale skin",
            "value": "yes",
            "confidence": 0.19
          },
          {
            "name": "pitch",
            "value": "-7.89",
            "confidence": 1.0
          },
          {
            "name": "pointy nose",
            "value": "yes",
            "confidence": 0.54
          },
          {
            "name": "race",
            "value": "white",
            "confidence": 1.0
          },
          {
            "name": "receding hairline",
            "value": "no",
            "confidence": 0.59
          },
          {
            "name": "rosy cheeks",
            "value": "yes",
            "confidence": 0.2
          },
          {
            "name": "sideburns",
            "value": "no",
            "confidence": 1.0
          },
          {
            "name": "straight hair",
            "value": "yes",
            "confidence": 0.32
          },
          {
            "name": "wavy hair",
            "value": "no",
            "confidence": 0.33
          },
          {
            "name": "wearing earrings",
            "value": "yes",
            "confidence": 0.08
          },
          {
            "name": "wearing hat",
            "value": "no",
            "confidence": 0.81
          },
          {
            "name": "wearing lipstick",
            "value": "yes",
            "confidence": 1.0
          },
          {
            "name": "wearing necklace",
            "value": "no",
            "confidence": 0.04
          },
          {
            "name": "wearing necktie",
            "value": "no",
            "confidence": 1.0
          },
          {
            "name": "yaw",
            "value": "-1.99",
            "confidence": 1.0
          },
          {
            "name": "young",
            "value": "yes",
            "confidence": 0.73
          }
        ],
        "person_id": "",
        "appearance_id": 0,
        "start": "00:00:00",
        "duration": "00:00:00"
      },
      {
        "face_uuid": "36dc14fe-1536-11e9-99c4-0cc47a6c4dbd",
        "media_uuid": "374ff712-d61b-4ca5-81f6-10f3526744e9",
        "x": 156.25,
        "y": 194.38,
        "width": 186.15,
        "height": 235.08,
        "angle": -5.2901,
        "detection_score": 1.0,
        "points": [
          {
            "x": 91.12,
            "y": 165.41,
            "type": 512,
            "name": "basic eye left"
          },
          {
            "x": 176.26,
            "y": 173.29,
            "type": 768,
            "name": "basic eye right"
          },
          {
            "x": 74.26,
            "y": 163.93,
            "type": 1024,
            "name": "basic eye left outer"
          },
          {
            "x": 195.97,
            "y": 175.23,
            "type": 1280,
            "name": "basic eye right outer"
          },
          {
            "x": 107.25,
            "y": 168.31,
            "type": 1536,
            "name": "basic eye left inner"
          },
          {
            "x": 156.48,
            "y": 172.93,
            "type": 1792,
            "name": "basic eye right inner"
          },
          {
            "x": 94.66,
            "y": 258.43,
            "type": 2048,
            "name": "basic mouth left"
          },
          {
            "x": 161.24,
            "y": 264.73,
            "type": 2304,
            "name": "basic mouth right"
          },
          {
            "x": 114.82,
            "y": 226.73,
            "type": 2560,
            "name": "basic nose tip"
          },
          {
            "x": 126.55,
            "y": 262.45,
            "type": 2816,
            "name": "basic mouth center"
          },
          {
            "x": 126.55,
            "y": 262.45,
            "type": 3072,
            "name": "basic eyebrow left"
          },
          {
            "x": 126.55,
            "y": 262.45,
            "type": 3328,
            "name": "basic eyebrow left inner corner"
          },
          {
            "x": 126.55,
            "y": 262.45,
            "type": 3584,
            "name": "basic eyebrow left outer corner"
          },
          {
            "x": 126.55,
            "y": 262.45,
            "type": 3840,
            "name": "basic eyebrow right"
          },
          {
            "x": 126.55,
            "y": 262.45,
            "type": 4096,
            "name": "basic eyebrow right inner corner"
          },
          {
            "x": 126.55,
            "y": 262.45,
            "type": 4352,
            "name": "basic eyebrow right outer corner"
          },
          {
            "x": 126.55,
            "y": 262.45,
            "type": 4608,
            "name": "basic chin bottom"
          },
          {
            "x": 126.55,
            "y": 262.45,
            "type": 4864,
            "name": "basic chin left"
          },
          {
            "x": 126.55,
            "y": 262.45,
            "type": 5120,
            "name": "basic chin right"
          },
          {
            "x": 100.05,
            "y": 228.21,
            "type": 5376,
            "name": "basic nose left"
          },
          {
            "x": 144.14,
            "y": 232.03,
            "type": 5632,
            "name": "basic nose right"
          }
        ],
        "user_points": null,
        "tags": [
          {
            "name": "5oclock shadow",
            "value": "no",
            "confidence": 1.0
          },
          {
            "name": "age",
            "value": "15",
            "confidence": 0.6
          },
          {
            "name": "arched eyebrows",
            "value": "no",
            "confidence": 0.76
          },
          {
            "name": "attractive",
            "value": "yes",
            "confidence": 0.45
          },
          {
            "name": "bags under eyes",
            "value": "no",
            "confidence": 1.0
          },
          {
            "name": "bald",
            "value": "no",
            "confidence": 0.85
          },
          {
            "name": "bangs",
            "value": "yes",
            "confidence": 0.98
          },
          {
            "name": "beard",
            "value": "no",
            "confidence": 1.0
          },
          {
            "name": "big lips",
            "value": "no",
            "confidence": 0.46
          },
          {
            "name": "big nose",
            "value": "no",
            "confidence": 1.0
          },
          {
            "name": "black hair",
            "value": "no",
            "confidence": 0.72
          },
          {
            "name": "blond hair",
            "value": "yes",
            "confidence": 0.48
          },
          {
            "name": "blurry",
            "value": "no",
            "confidence": 0.52
          },
          {
            "name": "brown hair",
            "value": "no",
            "confidence": 0.48
          },
          {
            "name": "bushy eyebrows",
            "value": "no",
            "confidence": 0.9
          },
          {
            "name": "chubby",
            "value": "no",
            "confidence": 1.0
          },
          {
            "name": "double chin",
            "value": "no",
            "confidence": 1.0
          },
          {
            "name": "expression",
            "value": "neutral",
            "confidence": 0.71
          },
          {
            "name": "gender",
            "value": "female",
            "confidence": 0.9
          },
          {
            "name": "glasses",
            "value": "no",
            "confidence": 1.0
          },
          {
            "name": "goatee",
            "value": "no",
            "confidence": 0.98
          },
          {
            "name": "gray hair",
            "value": "no",
            "confidence": 0.69
          },
          {
            "name": "heavy makeup",
            "value": "yes",
            "confidence": 0.58
          },
          {
            "name": "high cheekbones",
            "value": "no",
            "confidence": 0.68
          },
          {
            "name": "mouth open",
            "value": "no",
            "confidence": 0.81
          },
          {
            "name": "mustache",
            "value": "no",
            "confidence": 0.98
          },
          {
            "name": "narrow eyes",
            "value": "no",
            "confidence": 0.74
          },
          {
            "name": "oval face",
            "value": "yes",
            "confidence": 0.6
          },
          {
            "name": "pale skin",
            "value": "yes",
            "confidence": 0.61
          },
          {
            "name": "pitch",
            "value": "-6.08",
            "confidence": 1.0
          },
          {
            "name": "pointy nose",
            "value": "no",
            "confidence": 0.2
          },
          {
            "name": "race",
            "value": "white",
            "confidence": 0.99
          },
          {
            "name": "receding hairline",
            "value": "no",
            "confidence": 1.0
          },
          {
            "name": "rosy cheeks",
            "value": "no",
            "confidence": 0.72
          },
          {
            "name": "sideburns",
            "value": "no",
            "confidence": 1.0
          },
          {
            "name": "straight hair",
            "value": "yes",
            "confidence": 0.24
          },
          {
            "name": "wavy hair",
            "value": "no",
            "confidence": 0.35
          },
          {
            "name": "wearing earrings",
            "value": "no",
            "confidence": 0.66
          },
          {
            "name": "wearing hat",
            "value": "no",
            "confidence": 0.6
          },
          {
            "name": "wearing lipstick",
            "value": "yes",
            "confidence": 0.58
          },
          {
            "name": "wearing necklace",
            "value": "no",
            "confidence": 0.35
          },
          {
            "name": "wearing necktie",
            "value": "no",
            "confidence": 1.0
          },
          {
            "name": "yaw",
            "value": "46.16",
            "confidence": 1.0
          },
          {
            "name": "young",
            "value": "yes",
            "confidence": 0.75
          }
        ],
        "person_id": "",
        "appearance_id": 0,
        "start": "00:00:00",
        "duration": "00:00:00"
      }
    ],
    "tags": null,
    "original_filename": "https://raw.githubusercontent.com/sarkrui/Hairstyle60k/master/Dataset/Cute_Ponytails/IMG_18.jpg",
    "duration": "00:00:00"
  },
  "recognize": null
}