{
  "media": {
    "media_uuid": "c228ab4a-90d4-4684-a1bb-1d075d915c80",
    "checksum": "124feeccab4d1d173830c37cba961a5b041c22da32ce88105d150025867be4ea",
    "faces": [
      {
        "face_uuid": "72a641c7-1535-11e9-99c4-0cc47a6c4dbd",
        "media_uuid": "c228ab4a-90d4-4684-a1bb-1d075d915c80",
        "x": 298.0,
        "y": 254.5,
        "width": 160.48,
        "height": 186.27,
        "angle": -14.2219,
        "detection_score": 1.0,
        "points": [
          {
            "x": 285.79,
            "y": 237.81,
            "type": 512,
            "name": "basic eye left"
          },
          {
            "x": 351.66,
            "y": 254.5,
            "type": 768,
            "name": "basic eye right"
          },
          {
            "x": 270.12,
            "y": 234.82,
            "type": 1024,
            "name": "basic eye left outer"
          },
          {
            "x": 364.41,
            "y": 258.35,
            "type": 1280,
            "name": "basic eye right outer"
          },
          {
            "x": 300.99,
            "y": 241.34,
            "type": 1536,
            "name": "basic eye left inner"
          },
          {
            "x": 338.79,
            "y": 251.2,
            "type": 1792,
            "name": "basic eye right inner"
          },
          {
            "x": 274.65,
            "y": 306.8,
            "type": 2048,
            "name": "basic mouth left"
          },
          {
            "x": 320.8,
            "y": 320.41,
            "type": 2304,
            "name": "basic mouth right"
          },
          {
            "x": 323.1,
            "y": 285.34,
            "type": 2560,
            "name": "basic nose tip"
          },
          {
            "x": 299.07,
            "y": 313.68,
            "type": 2816,
            "name": "basic mouth center"
          },
          {
            "x": 299.07,
            "y": 313.68,
            "type": 3072,
            "name": "basic eyebrow left"
          },
          {
            "x": 299.07,
            "y": 313.68,
            "type": 3328,
            "name": "basic eyebrow left inner corner"
          },
          {
            "x": 299.07,
            "y": 313.68,
            "type": 3584,
            "name": "basic eyebrow left outer corner"
          },
          {
            "x": 299.07,
            "y": 313.68,
            "type": 3840,
            "name": "basic eyebrow right"
          },
          {
            "x": 299.07,
            "y": 313.68,
            "type": 4096,
            "name": "basic eyebrow right inner corner"
          },
          {
            "x": 299.07,
            "y": 313.68,
            "type": 4352,
            "name": "basic eyebrow right outer corner"
          },
          {
            "x": 299.07,
            "y": 313.68,
            "type": 4608,
            "name": "basic chin bottom"
          },
          {
            "x": 299.07,
            "y": 313.68,
            "type": 4864,
            "name": "basic chin left"
          },
          {
            "x": 299.07,
            "y": 313.68,
            "type": 5120,
            "name": "basic chin right"
          },
          {
            "x": 298.18,
            "y": 283.78,
            "type": 5376,
            "name": "basic nose left"
          },
          {
            "x": 331.74,
            "y": 292.43,
            "type": 5632,
            "name": "basic nose right"
          }
        ],
        "user_points": null,
        "tags": [
          {
            "name": "5oclock shadow",
            "value": "no",
            "confidence": 1.0
          },
          {
            "name": "age",
            "value": "20",
            "confidence": 0.6
          },
          {
            "name": "arched eyebrows",
            "value": "no",
            "confidence": 0.64
          },
          {
            "name": "attractive",
            "value": "no",
            "confidence": 0.26
          },
          {
            "name": "bags under eyes",
            "value": "no",
            "confidence": 1.0
          },
          {
            "name": "bald",
            "value": "no",
            "confidence": 1.0
          },
          {
            "name": "bangs",
            "value": "no",
            "confidence": 0.87
          },
          {
            "name": "beard",
            "value": "no",
            "confidence": 1.0
          },
          {
            "name": "big lips",
            "value": "no",
            "confidence": 0.39
          },
          {
            "name": "big nose",
            "value": "no",
            "confidence": 1.0
          },
          {
            "name": "black hair",
            "value": "no",
            "confidence": 0.55
          },
          {
            "name": "blond hair",
            "value": "no",
            "confidence": 0.63
          },
          {
            "name": "blurry",
            "value": "yes",
            "confidence": 0.42
          },
          {
            "name": "brown hair",
            "value": "yes",
            "confidence": 0.01
          },
          {
            "name": "bushy eyebrows",
            "value": "no",
            "confidence": 0.79
          },
          {
            "name": "chubby",
            "value": "no",
            "confidence": 0.99
          },
          {
            "name": "double chin",
            "value": "no",
            "confidence": 1.0
          },
          {
            "name": "expression",
            "value": "neutral",
            "confidence": 0.76
          },
          {
            "name": "gender",
            "value": "female",
            "confidence": 0.51
          },
          {
            "name": "glasses",
            "value": "no",
            "confidence": 1.0
          },
          {
            "name": "goatee",
            "value": "no",
            "confidence": 1.0
          },
          {
            "name": "gray hair",
            "value": "no",
            "confidence": 0.99
          },
          {
            "name": "heavy makeup",
            "value": "no",
            "confidence": 0.73
          },
          {
            "name": "high cheekbones",
            "value": "no",
            "confidence": 0.99
          },
          {
            "name": "mouth open",
            "value": "no",
            "confidence": 0.32
          },
          {
            "name": "mustache",
            "value": "no",
            "confidence": 1.0
          },
          {
            "name": "narrow eyes",
            "value": "yes",
            "confidence": 0.12
          },
          {
            "name": "oval face",
            "value": "no",
            "confidence": 0.3
          },
          {
            "name": "pale skin",
            "value": "yes",
            "confidence": 0.28
          },
          {
            "name": "pitch",
            "value": "-7.07",
            "confidence": 1.0
          },
          {
            "name": "pointy nose",
            "value": "no",
            "confidence": 0.24
          },
          {
            "name": "race",
            "value": "asian",
            "confidence": 0.99
          },
          {
            "name": "receding hairline",
            "value": "no",
            "confidence": 0.52
          },
          {
            "name": "rosy cheeks",
            "value": "no",
            "confidence": 1.0
          },
          {
            "name": "sideburns",
            "value": "no",
            "confidence": 1.0
          },
          {
            "name": "straight hair",
            "value": "no",
            "confidence": 0.61
          },
          {
            "name": "wavy hair",
            "value": "yes",
            "confidence": 0.03
          },
          {
            "name": "wearing earrings",
            "value": "no",
            "confidence": 0.15
          },
          {
            "name": "wearing hat",
            "value": "no",
            "confidence": 0.1
          },
          {
            "name": "wearing lipstick",
            "value": "no",
            "confidence": 0.53
          },
          {
            "name": "wearing necklace",
            "value": "no",
            "confidence": 0.37
          },
          {
            "name": "wearing necktie",
            "value": "no",
            "confidence": 1.0
          },
          {
            "name": "yaw",
            "value": "-28.18",
            "confidence": 1.0
          },
          {
            "name": "young",
            "value": "yes",
            "confidence": 0.72
          }
        ],
        "person_id": "",
        "appearance_id": 0,
        "start": "00:00:00",
        "duration": "00:00:00"
      }
    ],
    "tags": null,
    "original_filename": "https://raw.githubusercontent.com/sarkrui/Hairstyle60k/master/Dataset/Long_Hair/IMG_2.jpg",
    "duration": "00:00:00"
  },
  "recognize": null
}